privacyidea/__init__.py
privacyidea/app.py
privacyidea/config.py
privacyidea/api/__init__.py
privacyidea/api/application.py
privacyidea/api/audit.py
privacyidea/api/auth.py
privacyidea/api/before_after.py
privacyidea/api/caconnector.py
privacyidea/api/clienttype.py
privacyidea/api/container.py
privacyidea/api/event.py
privacyidea/api/healthcheck.py
privacyidea/api/info.py
privacyidea/api/machine.py
privacyidea/api/machineresolver.py
privacyidea/api/monitoring.py
privacyidea/api/periodictask.py
privacyidea/api/policy.py
privacyidea/api/privacyideaserver.py
privacyidea/api/radiusserver.py
privacyidea/api/realm.py
privacyidea/api/recover.py
privacyidea/api/register.py
privacyidea/api/resolver.py
privacyidea/api/serviceid.py
privacyidea/api/smsgateway.py
privacyidea/api/smtpserver.py
privacyidea/api/subscriptions.py
privacyidea/api/system.py
privacyidea/api/token.py
privacyidea/api/tokengroup.py
privacyidea/api/ttype.py
privacyidea/api/user.py
privacyidea/api/validate.py
privacyidea/api/lib/__init__.py
privacyidea/api/lib/decorators.py
privacyidea/api/lib/policyhelper.py
privacyidea/api/lib/postpolicy.py
privacyidea/api/lib/prepolicy.py
privacyidea/api/lib/utils.py
privacyidea/cli/__init__.py
privacyidea/cli/pimanage/__init__.py
privacyidea/cli/pimanage/admin.py
privacyidea/cli/pimanage/api.py
privacyidea/cli/pimanage/audit.py
privacyidea/cli/pimanage/backup.py
privacyidea/cli/pimanage/challenge.py
privacyidea/cli/pimanage/main.py
privacyidea/cli/pimanage/pi_config.py
privacyidea/cli/pimanage/pi_setup.py
privacyidea/cli/pimanage/token.py
privacyidea/cli/pitokenjanitor/__init__.py
privacyidea/cli/pitokenjanitor/main.py
privacyidea/cli/pitokenjanitor/utils/__init__.py
privacyidea/cli/pitokenjanitor/utils/findtokens.py
privacyidea/cli/pitokenjanitor/utils/importtokens.py
privacyidea/cli/pitokenjanitor/utils/updatetokens.py
privacyidea/cli/privacyideatokenjanitor/__init__.py
privacyidea/cli/privacyideatokenjanitor/findtokens.py
privacyidea-3.12.1.dist-info/licenses/LICENSE
privacyidea-3.12.1.dist-info/METADATA
privacyidea-3.12.1.dist-info/WHEEL
privacyidea-3.12.1.dist-info/entry_points.txt
privacyidea-3.12.1.dist-info/top_level.txt
privacyidea-3.12.1.dist-info/RECORD
