Metadata-Version: 2.4
Name: privacyIDEA
Version: 3.12.1
Summary: privacyIDEA: multifactor authentication management system
Author-email: Cornelius Kölbel <cornelius@privacyidea.org>
Maintainer-email: Cornelius Kölbel <cornelius@privacyidea.org>
License-Expression: AGPL-3.0-or-later
Project-URL: Homepage, https://privacyidea.org
Project-URL: Documentation, https://privacyidea.readthedocs.io
Project-URL: Source Code, https://github.com/privacyidea/privacyidea
Project-URL: Changelog, https://github.com/privacyidea/privacyidea/blob/master/Changelog
Project-URL: Forum, https://community.privacyidea.org
Keywords: OTP,two-factor authentication,management,security,2fa,mfa
Classifier: Framework :: Flask
Classifier: Programming Language :: Python
Classifier: Development Status :: 5 - Production/Stable
Classifier: Intended Audience :: System Administrators
Classifier: Natural Language :: English
Classifier: Operating System :: POSIX :: Linux
Classifier: Topic :: Internet
Classifier: Topic :: Security
Classifier: Topic :: System :: Systems Administration :: Authentication/Directory
Classifier: Programming Language :: Python
Classifier: Programming Language :: Python :: 3
Classifier: Programming Language :: Python :: 3.9
Classifier: Programming Language :: Python :: 3.10
Classifier: Programming Language :: Python :: 3.11
Classifier: Programming Language :: Python :: 3.12
Classifier: Programming Language :: Python :: 3.13
Requires-Python: >=3.9
License-File: LICENSE
Requires-Dist: argon2_cffi
Requires-Dist: beautifulsoup4[lxml]
Requires-Dist: cbor2
Requires-Dist: configobj
Requires-Dist: croniter
Requires-Dist: cryptography
Requires-Dist: defusedxml
Requires-Dist: Flask
Requires-Dist: Flask-Babel
Requires-Dist: Flask-Migrate
Requires-Dist: Flask-SQLAlchemy
Requires-Dist: Flask-Versioned
Requires-Dist: feedparser
Requires-Dist: google-auth
Requires-Dist: grpcio
Requires-Dist: huey[redis]
Requires-Dist: ldap3<2.9
Requires-Dist: msal
Requires-Dist: netaddr
Requires-Dist: passlib[bcrypt]
Requires-Dist: protobuf
Requires-Dist: pydash
Requires-Dist: PyJWT
Requires-Dist: PyMySQL
Requires-Dist: pyOpenSSL
Requires-Dist: pyrad
Requires-Dist: python-dateutil
Requires-Dist: python-gnupg
Requires-Dist: PyYAML
Requires-Dist: requests
Requires-Dist: segno
Requires-Dist: smpplib
Requires-Dist: SQLAlchemy<2.0
Requires-Dist: webauthn
Provides-Extra: test
Requires-Dist: mock; extra == "test"
Requires-Dist: pyparsing; extra == "test"
Requires-Dist: pytest; extra == "test"
Requires-Dist: pytest-cov; extra == "test"
Requires-Dist: responses; extra == "test"
Requires-Dist: testfixtures; extra == "test"
Provides-Extra: doc
Requires-Dist: Pallets-Sphinx-Themes; extra == "doc"
Requires-Dist: Sphinx; extra == "doc"
Requires-Dist: sphinxcontrib-httpdomain; extra == "doc"
Requires-Dist: sphinxcontrib-spelling; extra == "doc"
Requires-Dist: setuptools-scm; extra == "doc"
Provides-Extra: postgres
Requires-Dist: psycopg2; extra == "postgres"
Provides-Extra: hsm
Requires-Dist: PyKCS11; extra == "hsm"
Provides-Extra: kerberos
Requires-Dist: gssapi; extra == "kerberos"
Dynamic: license-file
